.cvsignore
CHANGES
Copyright
MANIFEST.in
Makefile
README
RELEASE
newver.py
setup.cfg
setup.py
ZSI/.cvsignore
ZSI/LBNLCopyright
ZSI/ServiceContainer.py
ZSI/ServiceProxy.py
ZSI/TC.py
ZSI/TCapache.py
ZSI/TCcompound.py
ZSI/TCnumbers.py
ZSI/TCtimes.py
ZSI/__init__.py
ZSI/address.py
ZSI/auth.py
ZSI/client.py
ZSI/digest_auth.py
ZSI/dispatch.py
ZSI/fault.py
ZSI/parse.py
ZSI/resolvers.py
ZSI/typeinterpreter.py
ZSI/version.py
ZSI/writer.py
ZSI.egg-info/PKG-INFO
ZSI.egg-info/SOURCES.txt
ZSI.egg-info/top_level.txt
ZSI/generate/__init__.py
ZSI/generate/containers.py
ZSI/generate/pyclass.py
ZSI/generate/utility.py
ZSI/generate/wsdl2dispatch.py
ZSI/generate/wsdl2python.py
ZSI/wstools/.cvsignore
ZSI/wstools/Namespaces.py
ZSI/wstools/TimeoutSocket.py
ZSI/wstools/UserTuple.py
ZSI/wstools/Utility.py
ZSI/wstools/WSDLTools.py
ZSI/wstools/XMLSchema.py
ZSI/wstools/XMLname.py
ZSI/wstools/ZPL
ZSI/wstools/__init__.py
ZSI/wstools/c14n.py
ZSI/wstools/license.txt
ZSI/wstools/logging.py
ZSI/wstools/test/.cvsignore
ZSI/wstools/test/README
ZSI/wstools/test/__init__.py
ZSI/wstools/test/config.txt
ZSI/wstools/test/schema.tar.gz
ZSI/wstools/test/test_t1.py
ZSI/wstools/test/test_wsdl.py
ZSI/wstools/test/test_wstools.py
ZSI/wstools/test/test_wstools_net.py
ZSI/wstools/test/xmethods.tar.gz
doc/.cvsignore
doc/Makefile
doc/c01-intro.tex
doc/c02-samples.tex
doc/c02a-coverage.tex
doc/c03-except.tex
doc/c04-utils.tex
doc/c05-parse.tex
doc/c06-tc.tex
doc/c07-writer.tex
doc/c08-fault.tex
doc/c09-resolve.tex
doc/c10-dispatch.tex
doc/c11-wsdl.tex
doc/version.tex
doc/zsi.css
doc/zsi.html
doc/zsi.pdf
doc/zsi.ps
doc/zsi.tex
doc/zsi.xsd
doc/zsixsd.tex
doc/examples/client/receive_response/complex/binding.wsdl
doc/examples/client/receive_response/complex/interface.wsdl
doc/examples/client/receive_response/complex/types.xsd
doc/examples/client/receive_response/complex/manual/.cvsignore
doc/examples/client/receive_response/complex/manual/ComplexTypes.py
doc/examples/client/receive_response/complex/manual/client.py
doc/examples/client/receive_response/complex/server/.cvsignore
