Metadata-Version: 1.0
Name: ZSI
Version: 2.0-rc1
Summary: Zolera SOAP Infrastructure
Home-page: http://pywebsvcs.sf.net/
Author: Rich Salz, et al
Author-email: pywebsvcs-talk@lists.sf.net
License: Python
Platform: UNKNOWN
